{
  "osRoles": {
    "name": "Выберите Ваши операционные системы.",
    "description": "Поставьте внизу соответствующую реакцию.",
    "roles": [
      {
        "name": "Windows",
        "color": null,
        "emoji": "windows",
        "ids": {
          "def": "807062011586281504"
        }
      },
      {
        "name": "Linux",
        "color": null,
        "emoji": "linux",
        "ids": {
          "def": "807062014207066154"
        }
      },
      {
        "name": "macOS",
        "color": null,
        "emoji": "macos",
        "ids": {
          "def": "807062016845938738"
        }
      }
    ]
  },
  "specificRoles": {
    "name": "Выберете Ваши направления в IT.",
    "description": "Аналогично поставьте внизу нужную реакцию.",
    "roles": [
      {
        "name": "3D",
        "color": "#10e2ca",
        "emoji": "3d",
        "ids": {
          "def": "807062065759780905",
          "pro": "807062042476937256",
          "check": "807062020771676180"
        }
      },
      {
        "name": "Neural",
        "color": "#27690b",
        "emoji": "neural",
        "ids": {
          "def": "807062068468645918",
          "pro": "807062044334489671",
          "check": "807062023309230100"
        }
      },
      {
        "name": "BotDev",
        "color": "#00b120",
        "emoji": "bot",
        "ids": {
          "def": "807062070482305084",
          "pro": "807062046663114783",
          "check": "807062025590800405"
        }
      },
      {
        "name": "AppDev",
        "color": "#1e28af",
        "emoji": "app",
        "ids": {
          "def": "807062072537120800",
          "pro": "807062049698873344",
          "check": "807062027549409313"
        }
      },
      {
        "name": "WebDev",
        "color": "#dbc500",
        "emoji": "web",
        "ids": {
          "def": "807062075578253323",
          "pro": "807062051792355348",
          "check": "807062029424394282"
        }
      },
      {
        "name": "Hardware",
        "color": "#34888F",
        "emoji": "hardware",
        "ids": {
          "def": "807062077590994984",
          "pro": "807062054162006096",
          "check": "807062031500181555"
        }
      },
      {
        "name": "GameDev",
        "color": "#e4047e",
        "emoji": "game",
        "ids": {
          "def": "807062079772295208",
          "pro": "807062056485781554",
          "check": "807062034335531018"
        }
      },
      {
        "name": "MobileDev",
        "color": "#3fb48a",
        "emoji": "mobile",
        "ids": {
          "def": "807062083460005908",
          "pro": "807062058503241759",
          "check": "807062036231225384"
        }
      },
      {
        "name": "Designer",
        "color": "#7914d3",
        "emoji": "design",
        "ids": {
          "def": "807062086487900190",
          "pro": "807062060793724948",
          "check": "807062038106341376"
        }
      }
    ]
  },
  "languageRoles": {
    "name": "Выберите языки, которые Вы изучаете или знаете.",
    "description": "Проставьте необходимые Вам реакции для получения ролей.",
    "roles": [
      {
        "name": "JavaScript",
        "color": "#F3D83F",
        "emoji": "js",
        "ids": {
          "def": "807062182709690369",
          "pro": "807062133526364180",
          "check": "807062090309304341"
        }
      },
      {
        "name": "Java",
        "color": "#E86B21",
        "emoji": "java",
        "ids": {
          "def": "807062185901686835",
          "pro": "807062136517820446",
          "check": "807062093278740490"
        }
      },
      {
        "name": "Python",
        "color": "#4eca16",
        "emoji": "python",
        "ids": {
          "def": "807062188757745714",
          "pro": "807062139071496213",
          "check": "807062095988260934"
        }
      },
      {
        "name": "Kotlin",
        "color": "#6272D6",
        "emoji": "kotlin",
        "ids": {
          "def": "807062192490414100",
          "pro": "807062141906845776",
          "check": "807062098144133151"
        }
      },
      {
        "name": "Go",
        "color": "#00A7CD",
        "emoji": "go",
        "ids": {
          "def": "807062195363512321",
          "pro": "807062144570884096",
          "check": "807062101217902622"
        }
      },
      {
        "name": "C#",
        "color": "#994895",
        "emoji": "csharp",
        "ids": {
          "def": "807062198479618108",
          "pro": "807062147082485800",
          "check": "807062104208572436"
        }
      },
      {
        "name": "C++",
        "color": "#5995C8",
        "emoji": "cpp",
        "ids": {
          "def": "807062200694210583",
          "pro": "807062150819348480",
          "check": "807062106666958878"
        }
      },
      {
        "name": "C",
        "color": "#5469B7",
        "emoji": "c_",
        "ids": {
          "def": "807062204436185148",
          "pro": "807062153487843358",
          "check": "807062108919300136"
        }
      },
      {
        "name": "PHP",
        "color": "#7177AB",
        "emoji": "php",
        "ids": {
          "def": "807062207573524490",
          "pro": "807062157342408714",
          "check": "807062111661326356"
        }
      },
      {
        "name": "HTML",
        "color": "#F26134",
        "emoji": "html",
        "ids": {
          "def": "807062210831581204",
          "pro": "807062160232415272",
          "check": "807062113927299073"
        }
      },
      {
        "name": "CSS",
        "color": "#0063E5",
        "emoji": "css",
        "ids": {
          "def": "807062213046435853",
          "pro": "807062163834404894",
          "check": "807062116741021717"
        }
      },
      {
        "name": "Rust",
        "color": "#F57F26",
        "emoji": "rust",
        "ids": {
          "def": "807062216343289877",
          "pro": "807062167231791104",
          "check": "807062119132299275"
        }
      },
      {
        "name": "Dart",
        "color": "#005593",
        "emoji": "dart",
        "ids": {
          "def": "807062219808178206",
          "pro": "807062171300659221",
          "check": "807062121527246849"
        }
      },
      {
        "name": "Swift",
        "color": "#FC7C46",
        "emoji": "swift",
        "ids": {
          "def": "807062222559248415",
          "pro": "807062173925900310",
          "check": "807062124441501717"
        }
      },
      {
        "name": "Ruby",
        "color": "#CF1A18",
        "emoji": "ruby",
        "ids": {
          "def": "807062225113710644",
          "pro": "807062177428013056",
          "check": "807062126606024765"
        }
      }
    ]
  }
}